nteract_on_jupyter/__init__.py
nteract_on_jupyter/_version.py
nteract_on_jupyter/are-you-happy-now.ipynb
nteract_on_jupyter/config.py
nteract_on_jupyter/example.ipynb
nteract_on_jupyter/extension.py
nteract_on_jupyter/handlers.py
nteract_on_jupyter/index.html
nteract_on_jupyter/nteractapp.py
nteract_on_jupyter/package.json
nteract_on_jupyter/semver.py
nteract_on_jupyter/tsconfig.json
nteract_on_jupyter/utils.py
nteract_on_jupyter/webpack.config.js
nteract_on_jupyter/app/app.tsx
nteract_on_jupyter/app/bootstrap.tsx
nteract_on_jupyter/app/config.tsx
nteract_on_jupyter/app/fonts.ts
nteract_on_jupyter/app/globals.d.ts
nteract_on_jupyter/app/index.tsx
nteract_on_jupyter/app/notebook-menu.css
nteract_on_jupyter/app/store.ts
nteract_on_jupyter/app/components/editable-title-overlay.tsx
nteract_on_jupyter/app/components/last-saved.tsx
nteract_on_jupyter/app/components/nav.tsx
nteract_on_jupyter/app/components/themed-logo.tsx
nteract_on_jupyter/app/contents/directory.tsx
nteract_on_jupyter/app/contents/headers.tsx
nteract_on_jupyter/app/contents/index.tsx
nteract_on_jupyter/app/contents/notebook.tsx
nteract_on_jupyter/app/contents/file/index.tsx
nteract_on_jupyter/app/contents/file/text-file.tsx
nteract_on_jupyter/app/triggers/open-notebook.ts
nteract_on_jupyter/dist/1-98752ca41f105e9f25c5.bundle.js
nteract_on_jupyter/dist/1-98752ca41f105e9f25c5.bundle.js.map
nteract_on_jupyter/dist/1-c37a19e543310110e94c.bundle.js
nteract_on_jupyter/dist/1-c37a19e543310110e94c.bundle.js.map
nteract_on_jupyter/dist/1-c9b91341b3b06a3eaf41.bundle.js
nteract_on_jupyter/dist/1-c9b91341b3b06a3eaf41.bundle.js.map
nteract_on_jupyter/dist/14-30068e0e18dd55838bf6.bundle.js
nteract_on_jupyter/dist/14-30068e0e18dd55838bf6.bundle.js.map
nteract_on_jupyter/dist/14-3fe66a77c32c8fce833a.bundle.js
nteract_on_jupyter/dist/14-3fe66a77c32c8fce833a.bundle.js.map
nteract_on_jupyter/dist/14-78c54f3777ba6765e240.bundle.js
nteract_on_jupyter/dist/14-78c54f3777ba6765e240.bundle.js.map
nteract_on_jupyter-2.0.12.dist-info/METADATA
nteract_on_jupyter-2.0.12.dist-info/WHEEL
nteract_on_jupyter-2.0.12.dist-info/entry_points.txt
nteract_on_jupyter-2.0.12.dist-info/top_level.txt
nteract_on_jupyter-2.0.12.dist-info/RECORD
